rolling_token_auth/__init__.py
rolling_token_auth-0.1.2.dist-info/METADATA
rolling_token_auth-0.1.2.dist-info/WHEEL
rolling_token_auth-0.1.2.dist-info/top_level.txt
rolling_token_auth-0.1.2.dist-info/RECORD
