Metadata-Version: 2.1
Name: rolling-token-auth
Version: 0.1.2
Summary: Rolling Token verificator & generator
Home-page: https://github.com/alexeichhorn/python-rolling-token-auth
Author: Alexander Eichhorn
Author-email: 
License: UNKNOWN
Platform: UNKNOWN
Classifier: Programming Language :: Python :: 3
Classifier: License :: OSI Approved :: MIT License
Classifier: Operating System :: OS Independent
Requires-Python: >=3.6
Requires-Dist: cryptography (>=2.9.0)
